{
  "$schema": "https://json-schema.org/draft/2020-12/schema",
  "title": "Che Argentina Travel (Articles, EN)",
  "type": "object",
  "additionalProperties": true,
  "properties": {
    "id": {
      "type": "string"
    },
    "source": {
      "type": "string"
    },
    "lang": {
      "type": "string"
    },
    "title": {
      "type": "string"
    },
    "text": {
      "type": "string"
    },
    "domain": {
      "type": "string"
    },
    "content_hash": {
      "type": "string"
    }
  },
  "required": [
    "id",
    "source",
    "lang",
    "title",
    "text",
    "domain",
    "content_hash"
  ]
}
